gmoji/__init__.py
gmoji/gmoji.py
gmoji-0.0.2.dist-info/METADATA
gmoji-0.0.2.dist-info/WHEEL
gmoji-0.0.2.dist-info/top_level.txt
gmoji-0.0.2.dist-info/RECORD
